[
  {
    "id": "CV-OPP-FARRA1",
    "lead_id": "CV-LEAD-FARRA1",
    "nome_oportunidade": "Produção Audiovisual — FARRA (5 projetos)",
    "empresa": "FARRA",
    "tipo_servico": "Vídeo Publicitário",
    "valor_estimado": 35500,
    "stage": "Fechado Ganho",
    "probabilidade": 100,
    "owner": "Caza Vision",
    "data_abertura": "2024-01-01",
    "prazo_estimado": null,
    "proxima_acao": "",
    "data_proxima_acao": null,
    "risco": "Baixo",
    "motivo_perda": "",
    "observacoes": "5 projetos contratados — 2 em produção ativa",
    "data_ultima_interacao": "2024-03-15",
    "tipo_negocio": "Recorrente"
  },
  {
    "id": "CV-OPP-LIVE01",
    "lead_id": "CV-LEAD-LIVE01",
    "nome_oportunidade": "Cobertura de Eventos — LIVE! (4 eventos)",
    "empresa": "LIVE!",
    "tipo_servico": "Evento / Live",
    "valor_estimado": 22300,
    "stage": "Fechado Ganho",
    "probabilidade": 100,
    "owner": "Caza Vision",
    "data_abertura": "2024-01-01",
    "prazo_estimado": null,
    "proxima_acao": "",
    "data_proxima_acao": null,
    "risco": "Baixo",
    "motivo_perda": "",
    "observacoes": "4 eventos contratados — 1 em produção ativa",
    "data_ultima_interacao": "2024-04-10",
    "tipo_negocio": "Recorrente"
  },
  {
    "id": "CV-OPP-ATFIL1",
    "lead_id": "CV-LEAD-ATFIL1",
    "nome_oportunidade": "Coprodução Audiovisual — AT Films",
    "empresa": "AT Films",
    "tipo_servico": "Filme Institucional",
    "valor_estimado": 15300,
    "stage": "Fechado Ganho",
    "probabilidade": 100,
    "owner": "Caza Vision",
    "data_abertura": "2024-01-01",
    "prazo_estimado": null,
    "proxima_acao": "",
    "data_proxima_acao": null,
    "risco": "Baixo",
    "motivo_perda": "",
    "observacoes": "2 projetos contratados — 1 em produção ativa",
    "data_ultima_interacao": "2024-03-20",
    "tipo_negocio": "Projeto"
  },
  {
    "id": "CV-OPP-ESOP01",
    "lead_id": "CV-LEAD-ESOP01",
    "nome_oportunidade": "Produção Cultural Audiovisual — ESO ProArte",
    "empresa": "ESO ProArte",
    "tipo_servico": "Filme Institucional",
    "valor_estimado": 8000,
    "stage": "Fechado Ganho",
    "probabilidade": 100,
    "owner": "Caza Vision",
    "data_abertura": "2024-01-01",
    "prazo_estimado": null,
    "proxima_acao": "",
    "data_proxima_acao": null,
    "risco": "Baixo",
    "motivo_perda": "",
    "observacoes": "Projeto entregue",
    "data_ultima_interacao": "2024-02-28",
    "tipo_negocio": "Projeto"
  },
  {
    "id": "CV-OPP-VBARB1",
    "lead_id": "CV-LEAD-VBARB1",
    "nome_oportunidade": "Vídeo Publicitário — Vanessa Barbosa",
    "empresa": "Vanessa Barbosa",
    "tipo_servico": "Vídeo Publicitário",
    "valor_estimado": 6900,
    "stage": "Fechado Ganho",
    "probabilidade": 100,
    "owner": "Caza Vision",
    "data_abertura": "2024-01-01",
    "prazo_estimado": null,
    "proxima_acao": "",
    "data_proxima_acao": null,
    "risco": "Baixo",
    "motivo_perda": "",
    "observacoes": "Projeto entregue",
    "data_ultima_interacao": "2024-01-20",
    "tipo_negocio": "Projeto"
  },
  {
    "id": "CV-OPP-OTHON1",
    "lead_id": "CV-LEAD-OTHON1",
    "nome_oportunidade": "Produção Audiovisual — OTHON",
    "empresa": "OTHON",
    "tipo_servico": "Vídeo Publicitário",
    "valor_estimado": 6000,
    "stage": "Fechado Ganho",
    "probabilidade": 100,
    "owner": "Caza Vision",
    "data_abertura": "2024-01-01",
    "prazo_estimado": null,
    "proxima_acao": "",
    "data_proxima_acao": null,
    "risco": "Baixo",
    "motivo_perda": "",
    "observacoes": "Projeto em produção ativa",
    "data_ultima_interacao": "2024-04-01",
    "tipo_negocio": "Projeto"
  },
  {
    "id": "CV-OPP-PATRI1",
    "lead_id": "CV-LEAD-PATRI1",
    "nome_oportunidade": "Fotografia de Casamento — Patrick",
    "empresa": "Patrick",
    "tipo_servico": "Fotografia",
    "valor_estimado": 5000,
    "stage": "Fechado Ganho",
    "probabilidade": 100,
    "owner": "Caza Vision",
    "data_abertura": "2024-01-01",
    "prazo_estimado": null,
    "proxima_acao": "",
    "data_proxima_acao": null,
    "risco": "Baixo",
    "motivo_perda": "",
    "observacoes": "Casamento entregue",
    "data_ultima_interacao": null,
    "tipo_negocio": "Avulso"
  },
  {
    "id": "CV-OPP-MARI01",
    "lead_id": "CV-LEAD-MARI01",
    "nome_oportunidade": "Fotografia de Casamento — Mari",
    "empresa": "Mari",
    "tipo_servico": "Fotografia",
    "valor_estimado": 4000,
    "stage": "Fechado Ganho",
    "probabilidade": 100,
    "owner": "Caza Vision",
    "data_abertura": "2024-01-01",
    "prazo_estimado": null,
    "proxima_acao": "",
    "data_proxima_acao": null,
    "risco": "Baixo",
    "motivo_perda": "",
    "observacoes": "Casamento entregue",
    "data_ultima_interacao": "2024-01-05",
    "tipo_negocio": "Avulso"
  }
]
